{
  "user":[
    {"ID": "1001", "Nome": "João", "Sobrenome": "Silva", "Email": "joao.silva@email.com", "Idade": "28"},
    {"ID": "1002", "Nome": "Maria", "Sobrenome": "Santos", "Email": "maria.santos@email.com", "Idade": "34"},
    {"ID": "1003", "Nome": "Pedro", "Sobrenome": "Oliveira", "Email": "pedro.oliveira@email.com", "Idade": "22"},
    {"ID": "1004", "Nome": "Ana", "Sobrenome": "Pereira", "Email": "ana.pereira@email.com", "Idade": "30"},
    {"ID": "1005", "Nome": "Carlos", "Sobrenome": "Rodrigues", "Email": "carlos.rodrigues@email.com", "Idade": "26"},
    {"ID": "1006", "Nome": "Laura", "Sobrenome": "Fernandes", "Email": "laura.fernandes@email.com", "Idade": "29"},
    {"ID": "1007", "Nome": "Bruno", "Sobrenome": "Costa", "Email": "bruno.costa@email.com", "Idade": "31"},
    {"ID": "1008", "Nome": "Sofia", "Sobrenome": "Gonçalves", "Email": "sofia.goncalves@email.com", "Idade": "27"},
    {"ID": "1009", "Nome": "Marcos", "Sobrenome": "Santos", "Email": "marcos.santos@email.com", "Idade": "33"},
    {"ID": "1010", "Nome": "Julia", "Sobrenome": "Lima", "Email": "julia.lima@email.com", "Idade": "25"}
  ]
  "item":[]
}